motulator/__init__.py
motulator/helpers.py
motulator/plots.py
motulator/simulation.py
motulator/control/__init__.py
motulator/control/common.py
motulator/control/im_vector.py
motulator/control/im_vhz.py
motulator/control/sm_torque.py
motulator/control/sm_vector.py
motulator/model/__init__.py
motulator/model/converter.py
motulator/model/im.py
motulator/model/im_drive.py
motulator/model/mech.py
motulator/model/sm.py
motulator/model/sm_drive.py
forkofthemotulator-0.0.5.dist-info/LICENSE
forkofthemotulator-0.0.5.dist-info/METADATA
forkofthemotulator-0.0.5.dist-info/WHEEL
forkofthemotulator-0.0.5.dist-info/top_level.txt
forkofthemotulator-0.0.5.dist-info/RECORD
