Metadata-Version: 2.1
Name: forkofthemotulator
Version: 0.0.5
Summary: A package for the motulator fork
Home-page: https://github.com/JoonaKukkonen/motulator
Author: JoonaKukkonen
Author-email: joona.j.kukkonen@aalto.fi
Project-URL: Bug Tracker, https://github.com/JoonaKukkonen/motulator/issues
Classifier: Programming Language :: Python :: 3
Classifier: License :: OSI Approved :: MIT License
Classifier: Operating System :: OS Independent
Requires-Python: >=3.6
License-File: LICENSE
